<?xml version="1.0" encoding="utf-8"?>
<search>
  
  
  
  <entry>
    <title>布莱恩岛 - FUTURD一周年纪念作</title>
    <link href="/2021/07/18/Anniversary/"/>
    <url>/2021/07/18/Anniversary/</url>
    
    <content type="html"><![CDATA[]]></content>
    
    
    
    <tags>
      
      <tag>周年纪念</tag>
      
    </tags>
    
  </entry>
  
  
  
  <entry>
    <title>Re: 从零开始的博客建造之旅</title>
    <link href="/2021/03/03/Re-%E4%BB%8E%E9%9B%B6%E5%BC%80%E5%A7%8B%E7%9A%84%E5%8D%9A%E5%AE%A2%E5%BB%BA%E9%80%A0%E4%B9%8B%E6%97%85/"/>
    <url>/2021/03/03/Re-%E4%BB%8E%E9%9B%B6%E5%BC%80%E5%A7%8B%E7%9A%84%E5%8D%9A%E5%AE%A2%E5%BB%BA%E9%80%A0%E4%B9%8B%E6%97%85/</url>
    
    <content type="html"><![CDATA[<h1 id="前言"><a href="#前言" class="headerlink" title="前言"></a>前言</h1><p>写这篇文章的原因除了好长时间没更以外还有就是我的第一个域名到期了，就想着回顾一下一年来关于博客的历史</p><h1 id="初篇-201"><a href="#初篇-201" class="headerlink" title="初篇[ 201? ]"></a>初篇[ 201? ]</h1><p>当时就已经对这建站感到兴趣了，度娘以后找到一家自助建站的平台，他们又提供了二级域名，就这么得，我人生中的第一个站就这么来了。</p><hr><h1 id="月升-2020-3"><a href="#月升-2020-3" class="headerlink" title="月升[ 2020.3 ]"></a>月升[ 2020.3 ]</h1><p>房外的树叶沙沙的响，几对热恋中的人也在享受快乐，在这么个残月的夜晚中，一个小城镇的学生打开了他的电脑，不停的翻着QQ，呼吸越发急促，急忙打开了浏览器，输入了一串网址后，越来越兴奋，摸了摸自己的腰包，咬咬牙充了一块钱，打开了虚拟主机的控制面板，又下载了Wordpress用ftp传了上去，他根据自己在各种论坛和视频网站上所学的，买了第一个域名[ rblog.xyz ]。好景不长，那家主机商跑路了，但这个人他没有钱去买服务器，他的第一个博客就这么夭折了。但是他又遇到了一群同样是做博客的小伙伴，不过，那都是后事了……</p><h1 id="黎明-2020-4"><a href="#黎明-2020-4" class="headerlink" title="黎明[ 2020.4 ]"></a>黎明[ 2020.4 ]</h1><p>偶然的一次，在翻看酷安的时候，我看到了一条我一直没想起来谁发的动态，怀着希望，用QQ扫了下码，很快便进了群，不过我还是不放心，待了几天后才申请了一台服务器中一块空间的使用权。不过这次，因为是国内服务器，未成年的我不得不用了群主的二级域名，这次我很幸运，不仅收录不错，博客还运行了很长时间。与群友们的交流越来越多，我也学到了很多。哦，对了，它叫 “乐趣计划”。</p><h1 id="晴空-2020-7"><a href="#晴空-2020-7" class="headerlink" title="晴空[ 2020.7 ]"></a>晴空[ 2020.7 ]</h1><p>在三个月之后，我迫于不可抗力的因素，又搬站到了虚拟主机商，这段历史其实没什么好讲的，买了第二个域名[ fd648.cn ]<br>在8月份，腾讯云出了活动，我自己买了一台中国香港的服务器，同时又于DNSPod购买了[ futurd.cn ]使用至今。在2021的除夕当日，又购买了一台腾讯云学生轻量应用服务器( 不是打广告 )，在大年初一又迁移了本站。</p><h1 id="展望"><a href="#展望" class="headerlink" title="展望"></a>展望</h1><p>新年了，也没什么好说的，就祝大家新年快乐吧。也希望自己这一年多产出好文章，文笔越来越好。行了，就到这吧，大家新年快乐！</p><h1 id="后言"><a href="#后言" class="headerlink" title="后言"></a>后言</h1><p>写完以后看着标题要尬死我了（</p>]]></content>
    
    
    
    <tags>
      
      <tag>历史</tag>
      
    </tags>
    
  </entry>
  
  
  
  <entry>
    <title>在你的Linux发行版上安装 Zsh 并美化安装插件</title>
    <link href="/2021/03/03/%E5%9C%A8%E4%BD%A0%E7%9A%84Linux%E5%8F%91%E8%A1%8C%E7%89%88%E4%B8%8A%E5%AE%89%E8%A3%85Zsh%E5%B9%B6%E7%BE%8E%E5%8C%96%E5%AE%89%E8%A3%85%E6%8F%92%E4%BB%B6/"/>
    <url>/2021/03/03/%E5%9C%A8%E4%BD%A0%E7%9A%84Linux%E5%8F%91%E8%A1%8C%E7%89%88%E4%B8%8A%E5%AE%89%E8%A3%85Zsh%E5%B9%B6%E7%BE%8E%E5%8C%96%E5%AE%89%E8%A3%85%E6%8F%92%E4%BB%B6/</url>
    
    <content type="html"><![CDATA[<h1 id="前言"><a href="#前言" class="headerlink" title="前言"></a>前言</h1><p>Zsh是一款好用的Shell，配置后使用会比较有效率</p><hr><h1 id="安装"><a href="#安装" class="headerlink" title="安装"></a>安装</h1><p>查看你的Linux上装了哪些Shell</p><figure class="highlight shell"><table><tr><td class="gutter hljs"><div class="hljs code-wrapper"><pre><span class="line">1</span><br></pre></div></td><td class="code"><div class="hljs code-wrapper"><pre><code class="hljs shell">echo $SHELL<br></code></pre></div></td></tr></table></figure><h2 id="安装Zsh"><a href="#安装Zsh" class="headerlink" title="安装Zsh"></a>安装Zsh</h2><p>通过包管理器来安装<br>Debian系：</p><figure class="highlight shell"><table><tr><td class="gutter hljs"><div class="hljs code-wrapper"><pre><span class="line">1</span><br><span class="line">2</span><br></pre></div></td><td class="code"><div class="hljs code-wrapper"><pre><code class="hljs shell">sudo apt update<br>sudo apt install zsh -y<br></code></pre></div></td></tr></table></figure><p>RedHat系：</p><figure class="highlight shell"><table><tr><td class="gutter hljs"><div class="hljs code-wrapper"><pre><span class="line">1</span><br><span class="line">2</span><br></pre></div></td><td class="code"><div class="hljs code-wrapper"><pre><code class="hljs shell">sudo yum update<br>sudo yum install zsh -y<br></code></pre></div></td></tr></table></figure><p>Arch系：</p><figure class="highlight shell"><table><tr><td class="gutter hljs"><div class="hljs code-wrapper"><pre><span class="line">1</span><br><span class="line">2</span><br></pre></div></td><td class="code"><div class="hljs code-wrapper"><pre><code class="hljs shell">sudo pacman -Syu<br>sudo pacman -S zsh<br></code></pre></div></td></tr></table></figure><p>将Zsh设为默认Shell</p><figure class="highlight awk"><table><tr><td class="gutter hljs"><div class="hljs code-wrapper"><pre><span class="line">1</span><br></pre></div></td><td class="code"><div class="hljs code-wrapper"><pre><code class="hljs awk">chsh -s <span class="hljs-regexp">/bin/</span>zsh<br></code></pre></div></td></tr></table></figure><h2 id="Oh-My-Zsh介绍"><a href="#Oh-My-Zsh介绍" class="headerlink" title="Oh My Zsh介绍"></a>Oh My Zsh介绍</h2><p>Oh My Zsh：<a href="https://ohmyz.sh/" title="链接地址">链接地址</a><br>Oh My Zsh是一款<strong>开源，由社区驱动的管理你的Zsh配置的框架，可以让我们更简单的使用配置Zsh</strong></p><h2 id="Oh-My-Zsh安装"><a href="#Oh-My-Zsh安装" class="headerlink" title="Oh My Zsh安装"></a>Oh My Zsh安装</h2><h2 id="条件要求"><a href="#条件要求" class="headerlink" title="条件要求"></a>条件要求</h2><ul><li><p>Linux发行版安装cURL，Git</p></li><li><p>能够正常的连接网络</p><p>首先，运行以下命令</p></li></ul><figure class="highlight shell"><table><tr><td class="gutter hljs"><div class="hljs code-wrapper"><pre><span class="line">1</span><br></pre></div></td><td class="code"><div class="hljs code-wrapper"><pre><code class="hljs shell">sh -c &amp;quot;$(curl -fsSL https://raw.github.com/ohmyzsh/ohmyzsh/master/tools/install.sh)&amp;quot;<br></code></pre></div></td></tr></table></figure><p>如果无法下载，可按照以下步骤来解决</p><figure class="highlight shell"><table><tr><td class="gutter hljs"><div class="hljs code-wrapper"><pre><span class="line">1</span><br></pre></div></td><td class="code"><div class="hljs code-wrapper"><pre><code class="hljs shell">vim ~/install.sh<br></code></pre></div></td></tr></table></figure><p>按你键盘上的<code>i</code><br>复制以下内容并粘贴进去</p><figure class="highlight shell"><table><tr><td class="gutter hljs"><div class="hljs code-wrapper"><pre><span class="line">1</span><br><span class="line">2</span><br><span class="line">3</span><br><span class="line">4</span><br><span class="line">5</span><br><span class="line">6</span><br><span class="line">7</span><br><span class="line">8</span><br><span class="line">9</span><br><span class="line">10</span><br><span class="line">11</span><br><span class="line">12</span><br><span class="line">13</span><br><span class="line">14</span><br><span class="line">15</span><br><span class="line">16</span><br><span class="line">17</span><br><span class="line">18</span><br><span class="line">19</span><br><span class="line">20</span><br><span class="line">21</span><br><span class="line">22</span><br><span class="line">23</span><br><span class="line">24</span><br><span class="line">25</span><br><span class="line">26</span><br><span class="line">27</span><br><span class="line">28</span><br><span class="line">29</span><br><span class="line">30</span><br><span class="line">31</span><br><span class="line">32</span><br><span class="line">33</span><br><span class="line">34</span><br><span class="line">35</span><br><span class="line">36</span><br><span class="line">37</span><br><span class="line">38</span><br><span class="line">39</span><br><span class="line">40</span><br><span class="line">41</span><br><span class="line">42</span><br><span class="line">43</span><br><span class="line">44</span><br><span class="line">45</span><br><span class="line">46</span><br><span class="line">47</span><br><span class="line">48</span><br><span class="line">49</span><br><span class="line">50</span><br><span class="line">51</span><br><span class="line">52</span><br><span class="line">53</span><br><span class="line">54</span><br><span class="line">55</span><br><span class="line">56</span><br><span class="line">57</span><br><span class="line">58</span><br><span class="line">59</span><br><span class="line">60</span><br><span class="line">61</span><br><span class="line">62</span><br><span class="line">63</span><br><span class="line">64</span><br><span class="line">65</span><br><span class="line">66</span><br><span class="line">67</span><br><span class="line">68</span><br><span class="line">69</span><br><span class="line">70</span><br><span class="line">71</span><br><span class="line">72</span><br><span class="line">73</span><br><span class="line">74</span><br><span class="line">75</span><br><span class="line">76</span><br><span class="line">77</span><br><span class="line">78</span><br><span class="line">79</span><br><span class="line">80</span><br><span class="line">81</span><br><span class="line">82</span><br><span class="line">83</span><br><span class="line">84</span><br><span class="line">85</span><br><span class="line">86</span><br><span class="line">87</span><br><span class="line">88</span><br><span class="line">89</span><br><span class="line">90</span><br><span class="line">91</span><br><span class="line">92</span><br><span class="line">93</span><br><span class="line">94</span><br><span class="line">95</span><br><span class="line">96</span><br><span class="line">97</span><br><span class="line">98</span><br><span class="line">99</span><br><span class="line">100</span><br><span class="line">101</span><br><span class="line">102</span><br><span class="line">103</span><br><span class="line">104</span><br><span class="line">105</span><br><span class="line">106</span><br><span class="line">107</span><br><span class="line">108</span><br><span class="line">109</span><br><span class="line">110</span><br><span class="line">111</span><br><span class="line">112</span><br><span class="line">113</span><br><span class="line">114</span><br><span class="line">115</span><br><span class="line">116</span><br><span class="line">117</span><br><span class="line">118</span><br><span class="line">119</span><br><span class="line">120</span><br><span class="line">121</span><br><span class="line">122</span><br><span class="line">123</span><br><span class="line">124</span><br><span class="line">125</span><br><span class="line">126</span><br><span class="line">127</span><br><span class="line">128</span><br><span class="line">129</span><br><span class="line">130</span><br><span class="line">131</span><br><span class="line">132</span><br><span class="line">133</span><br><span class="line">134</span><br><span class="line">135</span><br><span class="line">136</span><br><span class="line">137</span><br><span class="line">138</span><br><span class="line">139</span><br><span class="line">140</span><br><span class="line">141</span><br><span class="line">142</span><br><span class="line">143</span><br><span class="line">144</span><br><span class="line">145</span><br><span class="line">146</span><br><span class="line">147</span><br><span class="line">148</span><br><span class="line">149</span><br><span class="line">150</span><br><span class="line">151</span><br><span class="line">152</span><br><span class="line">153</span><br><span class="line">154</span><br><span class="line">155</span><br><span class="line">156</span><br><span class="line">157</span><br><span class="line">158</span><br><span class="line">159</span><br><span class="line">160</span><br><span class="line">161</span><br><span class="line">162</span><br><span class="line">163</span><br><span class="line">164</span><br><span class="line">165</span><br><span class="line">166</span><br><span class="line">167</span><br><span class="line">168</span><br><span class="line">169</span><br><span class="line">170</span><br><span class="line">171</span><br><span class="line">172</span><br><span class="line">173</span><br><span class="line">174</span><br><span class="line">175</span><br><span class="line">176</span><br><span class="line">177</span><br><span class="line">178</span><br><span class="line">179</span><br><span class="line">180</span><br><span class="line">181</span><br><span class="line">182</span><br><span class="line">183</span><br><span class="line">184</span><br><span class="line">185</span><br><span class="line">186</span><br><span class="line">187</span><br><span class="line">188</span><br><span class="line">189</span><br><span class="line">190</span><br><span class="line">191</span><br><span class="line">192</span><br><span class="line">193</span><br><span class="line">194</span><br><span class="line">195</span><br><span class="line">196</span><br><span class="line">197</span><br><span class="line">198</span><br><span class="line">199</span><br><span class="line">200</span><br><span class="line">201</span><br><span class="line">202</span><br><span class="line">203</span><br><span class="line">204</span><br><span class="line">205</span><br><span class="line">206</span><br><span class="line">207</span><br><span class="line">208</span><br><span class="line">209</span><br><span class="line">210</span><br><span class="line">211</span><br><span class="line">212</span><br><span class="line">213</span><br><span class="line">214</span><br><span class="line">215</span><br><span class="line">216</span><br><span class="line">217</span><br><span class="line">218</span><br><span class="line">219</span><br><span class="line">220</span><br><span class="line">221</span><br><span class="line">222</span><br><span class="line">223</span><br><span class="line">224</span><br><span class="line">225</span><br><span class="line">226</span><br><span class="line">227</span><br><span class="line">228</span><br><span class="line">229</span><br><span class="line">230</span><br><span class="line">231</span><br><span class="line">232</span><br><span class="line">233</span><br><span class="line">234</span><br><span class="line">235</span><br><span class="line">236</span><br><span class="line">237</span><br><span class="line">238</span><br><span class="line">239</span><br><span class="line">240</span><br><span class="line">241</span><br><span class="line">242</span><br><span class="line">243</span><br><span class="line">244</span><br><span class="line">245</span><br><span class="line">246</span><br><span class="line">247</span><br><span class="line">248</span><br><span class="line">249</span><br><span class="line">250</span><br><span class="line">251</span><br><span class="line">252</span><br><span class="line">253</span><br><span class="line">254</span><br><span class="line">255</span><br><span class="line">256</span><br><span class="line">257</span><br><span class="line">258</span><br><span class="line">259</span><br><span class="line">260</span><br><span class="line">261</span><br><span class="line">262</span><br><span class="line">263</span><br><span class="line">264</span><br><span class="line">265</span><br><span class="line">266</span><br><span class="line">267</span><br><span class="line">268</span><br><span class="line">269</span><br><span class="line">270</span><br><span class="line">271</span><br><span class="line">272</span><br><span class="line">273</span><br><span class="line">274</span><br><span class="line">275</span><br><span class="line">276</span><br><span class="line">277</span><br><span class="line">278</span><br><span class="line">279</span><br><span class="line">280</span><br><span class="line">281</span><br><span class="line">282</span><br><span class="line">283</span><br><span class="line">284</span><br><span class="line">285</span><br><span class="line">286</span><br><span class="line">287</span><br><span class="line">288</span><br><span class="line">289</span><br><span class="line">290</span><br><span class="line">291</span><br><span class="line">292</span><br><span class="line">293</span><br><span class="line">294</span><br><span class="line">295</span><br></pre></div></td><td class="code"><div class="hljs code-wrapper"><pre><code class="hljs shell"><span class="hljs-meta">#</span><span class="bash">!/bin/sh</span><br><span class="hljs-meta">#</span><span class="bash"></span><br><span class="bash"><span class="hljs-comment"># This script should be run via curl:</span></span><br><span class="hljs-meta">#</span><span class="bash">   sh -c <span class="hljs-string">&quot;<span class="hljs-subst">$(curl -fsSL https://raw.githubusercontent.com/ohmyzsh/ohmyzsh/master/tools/install.sh)</span>&quot;</span></span><br><span class="hljs-meta">#</span><span class="bash"> or via wget:</span><br><span class="hljs-meta">#</span><span class="bash">   sh -c <span class="hljs-string">&quot;<span class="hljs-subst">$(wget -qO- https://raw.githubusercontent.com/ohmyzsh/ohmyzsh/master/tools/install.sh)</span>&quot;</span></span><br><span class="hljs-meta">#</span><span class="bash"> or via fetch:</span><br><span class="hljs-meta">#</span><span class="bash">   sh -c <span class="hljs-string">&quot;<span class="hljs-subst">$(fetch -o - https://raw.githubusercontent.com/ohmyzsh/ohmyzsh/master/tools/install.sh)</span>&quot;</span></span><br><span class="hljs-meta">#</span><span class="bash"></span><br><span class="bash"><span class="hljs-comment"># As an alternative, you can first download the install script and run it afterwards:</span></span><br><span class="hljs-meta">#</span><span class="bash">   wget https://raw.githubusercontent.com/ohmyzsh/ohmyzsh/master/tools/install.sh</span><br><span class="hljs-meta">#</span><span class="bash">   sh install.sh</span><br><span class="hljs-meta">#</span><span class="bash"></span><br><span class="bash"><span class="hljs-comment"># You can tweak the install behavior by setting variables when running the script. For</span></span><br><span class="hljs-meta">#</span><span class="bash"> example, to change the path to the Oh My Zsh repository:</span><br><span class="hljs-meta">#</span><span class="bash">   ZSH=~/.zsh sh install.sh</span><br><span class="hljs-meta">#</span><span class="bash"></span><br><span class="bash"><span class="hljs-comment"># Respects the following environment variables:</span></span><br><span class="hljs-meta">#</span><span class="bash">   ZSH     - path to the Oh My Zsh repository folder (default: <span class="hljs-variable">$HOME</span>/.oh-my-zsh)</span><br><span class="hljs-meta">#</span><span class="bash">   REPO    - name of the GitHub repo to install from (default: ohmyzsh/ohmyzsh)</span><br><span class="hljs-meta">#</span><span class="bash">   REMOTE  - full remote URL of the git repo to install (default: GitHub via HTTPS)</span><br><span class="hljs-meta">#</span><span class="bash">   BRANCH  - branch to check out immediately after install (default: master)</span><br><span class="hljs-meta">#</span><span class="bash"></span><br><span class="bash"><span class="hljs-comment"># Other options:</span></span><br><span class="hljs-meta">#</span><span class="bash">   CHSH       - <span class="hljs-string">&#x27;no&#x27;</span> means the installer will not change the default shell (default: yes)</span><br><span class="hljs-meta">#</span><span class="bash">   RUNZSH     - <span class="hljs-string">&#x27;no&#x27;</span> means the installer will not run zsh after the install (default: yes)</span><br><span class="hljs-meta">#</span><span class="bash">   KEEP_ZSHRC - <span class="hljs-string">&#x27;yes&#x27;</span> means the installer will not replace an existing .zshrc (default: no)</span><br><span class="hljs-meta">#</span><span class="bash"></span><br><span class="bash"><span class="hljs-comment"># You can also pass some arguments to the install script to set some these options:</span></span><br><span class="hljs-meta">#</span><span class="bash">   --skip-chsh: has the same behavior as setting CHSH to <span class="hljs-string">&#x27;no&#x27;</span></span><br><span class="hljs-meta">#</span><span class="bash">   --unattended: sets both CHSH and RUNZSH to <span class="hljs-string">&#x27;no&#x27;</span></span><br><span class="hljs-meta">#</span><span class="bash">   --keep-zshrc: sets KEEP_ZSHRC to <span class="hljs-string">&#x27;yes&#x27;</span></span><br><span class="hljs-meta">#</span><span class="bash"> For example:</span><br><span class="hljs-meta">#</span><span class="bash">   sh install.sh --unattended</span><br><span class="hljs-meta">#</span><span class="bash"> or:</span><br><span class="hljs-meta">#</span><span class="bash">   sh -c <span class="hljs-string">&quot;<span class="hljs-subst">$(curl -fsSL https://raw.githubusercontent.com/ohmyzsh/ohmyzsh/master/tools/install.sh)</span>&quot;</span> <span class="hljs-string">&quot;&quot;</span> --unattended</span><br><span class="hljs-meta">#</span><span class="bash"></span><br><span class="bash"><span class="hljs-built_in">set</span> -e</span><br><span class="hljs-meta"></span><br><span class="hljs-meta">#</span><span class="bash"> Default settings</span><br>ZSH=$&#123;ZSH:-~/.oh-my-zsh&#125;<br>REPO=$&#123;REPO:-ohmyzsh/ohmyzsh&#125;<br>REMOTE=$&#123;REMOTE:-https://github.com/$&#123;REPO&#125;.git&#125;<br>BRANCH=$&#123;BRANCH:-master&#125;<br><span class="hljs-meta"></span><br><span class="hljs-meta">#</span><span class="bash"> Other options</span><br>CHSH=$&#123;CHSH:-yes&#125;<br>RUNZSH=$&#123;RUNZSH:-yes&#125;<br>KEEP_ZSHRC=$&#123;KEEP_ZSHRC:-no&#125;<br><br><br>command_exists() &#123;<br>command -v &quot;$@&quot; &gt;/dev/null 2&gt;&amp;1<br>&#125;<br><br>error() &#123;<br>echo $&#123;RED&#125;&quot;Error: $@&quot;$&#123;RESET&#125; &gt;&amp;2<br>&#125;<br><br>underline() &#123;<br>echo &quot;$(printf &#x27;\033[4m&#x27;)$@$(printf &#x27;\033[24m&#x27;)&quot;<br>&#125;<br><br>setup_color() &#123;<br><span class="hljs-meta">#</span><span class="bash"> Only use colors <span class="hljs-keyword">if</span> connected to a terminal</span><br>if [ -t 1 ]; then<br>RED=$(printf &#x27;\033[31m&#x27;)<br>GREEN=$(printf &#x27;\033[32m&#x27;)<br>YELLOW=$(printf &#x27;\033[33m&#x27;)<br>BLUE=$(printf &#x27;\033[34m&#x27;)<br>BOLD=$(printf &#x27;\033[1m&#x27;)<br>RESET=$(printf &#x27;\033[m&#x27;)<br>else<br>RED=&quot;&quot;<br>GREEN=&quot;&quot;<br>YELLOW=&quot;&quot;<br>BLUE=&quot;&quot;<br>BOLD=&quot;&quot;<br>RESET=&quot;&quot;<br>fi<br>&#125;<br><br>setup_ohmyzsh() &#123;<br><span class="hljs-meta">#</span><span class="bash"> Prevent the cloned repository from having insecure permissions. Failing to <span class="hljs-keyword">do</span></span><br><span class="hljs-meta">#</span><span class="bash"> so causes compinit() calls to fail with <span class="hljs-string">&quot;command not found: compdef&quot;</span> errors</span><br><span class="hljs-meta">#</span><span class="bash"> <span class="hljs-keyword">for</span> users with insecure umasks (e.g., <span class="hljs-string">&quot;002&quot;</span>, allowing group writability). Note</span><br><span class="hljs-meta">#</span><span class="bash"> that this will be ignored under Cygwin by default, as Windows ACLs take</span><br><span class="hljs-meta">#</span><span class="bash"> precedence over umasks except <span class="hljs-keyword">for</span> filesystems mounted with option <span class="hljs-string">&quot;noacl&quot;</span>.</span><br>umask g-w,o-w<br><br>echo &quot;$&#123;BLUE&#125;Cloning Oh My Zsh...$&#123;RESET&#125;&quot;<br><br>command_exists git || &#123;<br>error &quot;git is not installed&quot;<br>exit 1<br>&#125;<br><br>if [ &quot;$OSTYPE&quot; = cygwin ] &amp;&amp; git --version | grep -q msysgit; then<br>error &quot;Windows/MSYS Git is not supported on Cygwin&quot;<br>error &quot;Make sure the Cygwin git package is installed and is first on the \$PATH&quot;<br>exit 1<br>fi<br><br>git clone -c core.eol=lf -c core.autocrlf=false \<br>-c fsck.zeroPaddedFilemode=ignore \<br>-c fetch.fsck.zeroPaddedFilemode=ignore \<br>-c receive.fsck.zeroPaddedFilemode=ignore \<br>--depth=1 --branch &quot;$BRANCH&quot; &quot;$REMOTE&quot; &quot;$ZSH&quot; || &#123;<br>error &quot;git clone of oh-my-zsh repo failed&quot;<br>exit 1<br>&#125;<br><br>echo<br>&#125;<br><br>setup_zshrc() &#123;<br><span class="hljs-meta">#</span><span class="bash"> Keep most recent old .zshrc at .zshrc.pre-oh-my-zsh, and older ones</span><br><span class="hljs-meta">#</span><span class="bash"> with datestamp of installation that moved them aside, so we never actually</span><br><span class="hljs-meta">#</span><span class="bash"> destroy a user<span class="hljs-string">&#x27;s original zshrc</span></span><br>echo &quot;$&#123;BLUE&#125;Looking for an existing zsh config...$&#123;RESET&#125;&quot;<br><span class="hljs-meta"></span><br><span class="hljs-meta">#</span><span class="bash"><span class="hljs-string"> Must use this exact name so uninstall.sh can find it</span></span><br>OLD_ZSHRC=~/.zshrc.pre-oh-my-zsh<br>if [ -f ~/.zshrc ] || [ -h ~/.zshrc ]; then<br><span class="hljs-meta">#</span><span class="bash"><span class="hljs-string"> Skip this if the user doesn&#x27;</span>t want to replace an existing .zshrc</span><br>if [ $KEEP_ZSHRC = yes ]; then<br>echo &quot;$&#123;YELLOW&#125;Found ~/.zshrc.$&#123;RESET&#125; $&#123;GREEN&#125;Keeping...$&#123;RESET&#125;&quot;<br>return<br>fi<br>if [ -e &quot;$OLD_ZSHRC&quot; ]; then<br>OLD_OLD_ZSHRC=&quot;$&#123;OLD_ZSHRC&#125;-$(date +%Y-%m-%d_%H-%M-%S)&quot;<br>if [ -e &quot;$OLD_OLD_ZSHRC&quot; ]; then<br>error &quot;$OLD_OLD_ZSHRC exists. Can&#x27;t back up $&#123;OLD_ZSHRC&#125;&quot;<br>error &quot;re-run the installer again in a couple of seconds&quot;<br>exit 1<br>fi<br>mv &quot;$OLD_ZSHRC&quot; &quot;$&#123;OLD_OLD_ZSHRC&#125;&quot;<br><br>echo &quot;$&#123;YELLOW&#125;Found old ~/.zshrc.pre-oh-my-zsh.&quot; \<br>&quot;$&#123;GREEN&#125;Backing up to $&#123;OLD_OLD_ZSHRC&#125;$&#123;RESET&#125;&quot;<br>fi<br>echo &quot;$&#123;YELLOW&#125;Found ~/.zshrc.$&#123;RESET&#125; $&#123;GREEN&#125;Backing up to $&#123;OLD_ZSHRC&#125;$&#123;RESET&#125;&quot;<br>mv ~/.zshrc &quot;$OLD_ZSHRC&quot;<br>fi<br><br>echo &quot;$&#123;GREEN&#125;Using the Oh My Zsh template file and adding it to ~/.zshrc.$&#123;RESET&#125;&quot;<br><br>sed &quot;/^export ZSH=/ c\\<br>export ZSH=\&quot;$ZSH\&quot;<br>&quot; &quot;$ZSH/templates/zshrc.zsh-template&quot; &gt; ~/.zshrc-omztemp<br>mv -f ~/.zshrc-omztemp ~/.zshrc<br><br>echo<br>&#125;<br><br>setup_shell() &#123;<br><span class="hljs-meta">#</span><span class="bash"> Skip setup <span class="hljs-keyword">if</span> the user wants or stdin is closed (not running interactively).</span><br>if [ $CHSH = no ]; then<br>return<br>fi<br><span class="hljs-meta"></span><br><span class="hljs-meta">#</span><span class="bash"> If this user<span class="hljs-string">&#x27;s login shell is already &quot;zsh&quot;, do not attempt to switch.</span></span><br>if [ &quot;$(basename &quot;$SHELL&quot;)&quot; = &quot;zsh&quot; ]; then<br>return<br>fi<br><span class="hljs-meta"></span><br><span class="hljs-meta">#</span><span class="bash"><span class="hljs-string"> If this platform doesn&#x27;</span>t provide a <span class="hljs-string">&quot;chsh&quot;</span> <span class="hljs-built_in">command</span>, bail out.</span><br>if ! command_exists chsh; then<br>cat &lt;&lt;-EOF<br>I can&#x27;t change your shell automatically because this system does not have chsh.<br><span class="hljs-meta">$</span><span class="bash">&#123;BLUE&#125;Please manually change your default shell to zsh<span class="hljs-variable">$&#123;RESET&#125;</span></span><br>EOF<br>return<br>fi<br><br>echo &quot;$&#123;BLUE&#125;Time to change your default shell to zsh:$&#123;RESET&#125;&quot;<br><span class="hljs-meta"></span><br><span class="hljs-meta">#</span><span class="bash"> Prompt <span class="hljs-keyword">for</span> user choice on changing the default login shell</span><br>printf &quot;$&#123;YELLOW&#125;Do you want to change your default shell to zsh? [Y/n]$&#123;RESET&#125; &quot;<br>read opt<br>case $opt in<br>y*|Y*|&quot;&quot;) echo &quot;Changing the shell...&quot; ;;<br>n*|N*) echo &quot;Shell change skipped.&quot;; return ;;<br>*) echo &quot;Invalid choice. Shell change skipped.&quot;; return ;;<br>esac<br><span class="hljs-meta"></span><br><span class="hljs-meta">#</span><span class="bash"> Check <span class="hljs-keyword">if</span> we<span class="hljs-string">&#x27;re running on Termux</span></span><br>case &quot;$PREFIX&quot; in<br>*com.termux*) termux=true; zsh=zsh ;;<br>*) termux=false ;;<br>esac<br><br>if [ &quot;$termux&quot; != true ]; then<br><span class="hljs-meta">#</span><span class="bash"><span class="hljs-string"> Test for the right location of the &quot;shells&quot; file</span></span><br>if [ -f /etc/shells ]; then<br>shells_file=/etc/shells<br>elif [ -f /usr/share/defaults/etc/shells ]; then # Solus OS<br>shells_file=/usr/share/defaults/etc/shells<br>else<br>error &quot;could not find /etc/shells file. Change your default shell manually.&quot;<br>return<br>fi<br><span class="hljs-meta"></span><br><span class="hljs-meta">#</span><span class="bash"><span class="hljs-string"> Get the path to the right zsh binary</span></span><br><span class="hljs-meta">#</span><span class="bash"><span class="hljs-string"> 1. Use the most preceding one based on $PATH, then check that it&#x27;</span>s <span class="hljs-keyword">in</span> the shells file</span><br><span class="hljs-meta">#</span><span class="bash"> 2. If that fails, get a zsh path from the shells file, <span class="hljs-keyword">then</span> check it actually exists</span><br>if ! zsh=$(which zsh) || ! grep -qx &quot;$zsh&quot; &quot;$shells_file&quot;; then<br>if ! zsh=$(grep &#x27;^/.*/zsh$&#x27; &quot;$shells_file&quot; | tail -1) || [ ! -f &quot;$zsh&quot; ]; then<br>error &quot;no zsh binary found or not present in &#x27;$shells_file&#x27;&quot;<br>error &quot;change your default shell manually.&quot;<br>return<br>fi<br>fi<br>fi<br><span class="hljs-meta"></span><br><span class="hljs-meta">#</span><span class="bash"> We<span class="hljs-string">&#x27;re going to change the default shell, so back up the current one</span></span><br>if [ -n &quot;$SHELL&quot; ]; then<br>echo $SHELL &gt; ~/.shell.pre-oh-my-zsh<br>else<br>grep &quot;^$USER:&quot; /etc/passwd | awk -F: &#x27;&#123;print $7&#125;&#x27; &gt; ~/.shell.pre-oh-my-zsh<br>fi<br><span class="hljs-meta"></span><br><span class="hljs-meta">#</span><span class="bash"><span class="hljs-string"> Actually change the default shell to zsh</span></span><br>if ! chsh -s &quot;$zsh&quot;; then<br>error &quot;chsh command unsuccessful. Change your default shell manually.&quot;<br>else<br>export SHELL=&quot;$zsh&quot;<br>echo &quot;$&#123;GREEN&#125;Shell successfully changed to &#x27;$zsh&#x27;.$&#123;RESET&#125;&quot;<br>fi<br><br>echo<br>&#125;<br><br>main() &#123;<br><span class="hljs-meta">#</span><span class="bash"><span class="hljs-string"> Run as unattended if stdin is closed</span></span><br>if [ ! -t 0 ]; then<br>RUNZSH=no<br>CHSH=no<br>fi<br><span class="hljs-meta"></span><br><span class="hljs-meta">#</span><span class="bash"><span class="hljs-string"> Parse arguments</span></span><br>while [ $# -gt 0 ]; do<br>case $1 in<br>--unattended) RUNZSH=no; CHSH=no ;;<br>--skip-chsh) CHSH=no ;;<br>--keep-zshrc) KEEP_ZSHRC=yes ;;<br>esac<br>shift<br>done<br><br>setup_color<br><br>if ! command_exists zsh; then<br>echo &quot;$&#123;YELLOW&#125;Zsh is not installed.$&#123;RESET&#125; Please install zsh first.&quot;<br>exit 1<br>fi<br><br>if [ -d &quot;$ZSH&quot; ]; then<br>cat &lt;&lt;-EOF<br><span class="hljs-meta">$</span><span class="bash"><span class="hljs-string">&#123;YELLOW&#125;You already have Oh My Zsh installed.$&#123;RESET&#125;</span></span><br>You&#x27;ll need to remove &#x27;$ZSH&#x27; if you want to reinstall.<br>EOF<br>exit 1<br>fi<br><br>setup_ohmyzsh<br>setup_zshrc<br>setup_shell<br><br>printf &quot;$GREEN&quot;<br>cat &lt;&lt;-&#x27;EOF&#x27;<br>         __                                     __<br>  ____  / /_     ____ ___  __  __   ____  _____/ /_<br> / __ \/ __ \   / __ `__ \/ / / /  /_  / / ___/ __ \<br>/ /_/ / / / /  / / / / / / /_/ /    / /_(__  ) / / /<br>\____/_/ /_/  /_/ /_/ /_/\__, /    /___/____/_/ /_/<br>                        /____/                       ....is now installed!<br>EOF<br>cat &lt;&lt;-EOF<br>Before you scream Oh My Zsh! please look over the ~/.zshrc file to select plugins, themes, and options.<br>• Follow us on Twitter: $(underline https://twitter.com/ohmyzsh)<br>• Join our Discord server: $(underline https://discord.gg/ohmyzsh)<br>• Get stickers, shirts, coffee mugs and other swag: $(underline https://shop.planetargon.com/collections/oh-my-zsh)<br>EOF<br>printf &quot;$RESET&quot;<br><br>if [ $RUNZSH = no ]; then<br>echo &quot;$&#123;YELLOW&#125;Run zsh to try it out.$&#123;RESET&#125;&quot;<br>exit<br>fi<br><br>exec zsh -l<br>&#125;<br><br>main &quot;$@&quot;<br></code></pre></div></td></tr></table></figure><p>按<code>Esc</code>,输入<code>:wq</code></p><h1 id="美化"><a href="#美化" class="headerlink" title="美化"></a>美化</h1><p>没什么好说的，接着看吧</p><h2 id="安装主题"><a href="#安装主题" class="headerlink" title="安装主题"></a>安装主题</h2><p>一个好用的主题能大大的提高Shell的颜值和工作效率，这里我们使用<strong>Powerlevel10k</strong><br><img src="http://fd-img.test.upcdn.net/images/prompt-styles-high-contrast.png"><br>首先克隆powerlevel10的仓库到主题文件夹</p><figure class="highlight shell"><table><tr><td class="gutter hljs"><div class="hljs code-wrapper"><pre><span class="line">1</span><br></pre></div></td><td class="code"><div class="hljs code-wrapper"><pre><code class="hljs shell">git clone https://github.com/romkatv/powerlevel10k.git $ZSH_CUSTOM/themes/powerlevel10k<br></code></pre></div></td></tr></table></figure><p>修改<code>.zshrc</code></p><figure class="highlight shell"><table><tr><td class="gutter hljs"><div class="hljs code-wrapper"><pre><span class="line">1</span><br></pre></div></td><td class="code"><div class="hljs code-wrapper"><pre><code class="hljs shell">vim ~/.zshrc<br></code></pre></div></td></tr></table></figure><p>将<code>ZSH_THEME=&quot;***&quot;</code>引号内的内容改为<code>powerlevel10k/powerlevel10k</code><br>使配置生效</p><figure class="highlight shell"><table><tr><td class="gutter hljs"><div class="hljs code-wrapper"><pre><span class="line">1</span><br></pre></div></td><td class="code"><div class="hljs code-wrapper"><pre><code class="hljs shell">source ~/.zshrc<br></code></pre></div></td></tr></table></figure><h2 id="安装字体"><a href="#安装字体" class="headerlink" title="安装字体"></a>安装字体</h2><p>因为这个主题有的字符需要安装支持的字体，否则看起来很糟糕，这里我们使用打了Nerd补丁的字体<br>Nerd Fonts官网:[链接](<a href="https://nerdfonts.com/">https://nerdfonts.com/</a> &quot;链接&quot;)<br>进入Downloads<br>，这里我选择了Hack字体于是我往下翻找到Hack字体，点击下载<br>字体安装请自行解决<br>接下来，向.zshrc修改这一条</p><figure class="highlight shell"><table><tr><td class="gutter hljs"><div class="hljs code-wrapper"><pre><span class="line">1</span><br></pre></div></td><td class="code"><div class="hljs code-wrapper"><pre><code class="hljs shell">POWERLEVEL9K_MODE=&#x27;nerdfont-complete&#x27;<br></code></pre></div></td></tr></table></figure><h2 id="安装插件"><a href="#安装插件" class="headerlink" title="安装插件"></a>安装插件</h2><h3 id="自动补全"><a href="#自动补全" class="headerlink" title="自动补全"></a>自动补全</h3><figure class="highlight shell"><table><tr><td class="gutter hljs"><div class="hljs code-wrapper"><pre><span class="line">1</span><br></pre></div></td><td class="code"><div class="hljs code-wrapper"><pre><code class="hljs shell">git clone https://github.com/zsh-users/zsh-autosuggestions $ZSH_CUSTOM/plugins/zsh-autosuggestions<br></code></pre></div></td></tr></table></figure><p>在<code>.zshrc</code>里找到<code>plugins</code>，加入<code>zsh-autosuggestions</code></p><h3 id="语法高亮"><a href="#语法高亮" class="headerlink" title="语法高亮"></a>语法高亮</h3><figure class="highlight shell"><table><tr><td class="gutter hljs"><div class="hljs code-wrapper"><pre><span class="line">1</span><br></pre></div></td><td class="code"><div class="hljs code-wrapper"><pre><code class="hljs shell">git clone https://github.com/zsh-users/zsh-syntax-highlighting.git $ZSH_CUSTOM/plugins/zsh-syntax-highlighting<br></code></pre></div></td></tr></table></figure><p>编辑<code>.zshrc</code>向<code>plugins</code>加入<code>zsh-syntax-highlighting</code></p>]]></content>
    
    
    
    <tags>
      
      <tag>Linux</tag>
      
      <tag>Zsh</tag>
      
    </tags>
    
  </entry>
  
  
  
  <entry>
    <title>用Termux在安卓手机中安装Linux</title>
    <link href="/2021/03/03/%E7%94%A8Termux%E5%9C%A8%E5%AE%89%E5%8D%93%E6%89%8B%E6%9C%BA%E4%B8%AD%E5%AE%89%E8%A3%85Linux/"/>
    <url>/2021/03/03/%E7%94%A8Termux%E5%9C%A8%E5%AE%89%E5%8D%93%E6%89%8B%E6%9C%BA%E4%B8%AD%E5%AE%89%E8%A3%85Linux/</url>
    
    <content type="html"><![CDATA[<h1 id="前言"><a href="#前言" class="headerlink" title="前言"></a>前言</h1><p>Termux是一款安卓手机可用的终端，可以模拟一部分Linux操作，但并不是完整的Linux系统，所以我们今天来用Termux安装完整版的Linux发行版系统</p><h1 id="准备工作"><a href="#准备工作" class="headerlink" title="准备工作"></a>准备工作</h1><blockquote><p>会打字<br>会粘贴复制<br>会用脑子</p></blockquote><h1 id="开始安装"><a href="#开始安装" class="headerlink" title="开始安装"></a>开始安装</h1><p>PS:由于本人文笔有限，请各位谅解，谢谢</p><p>Termux下载:<a href="https://f-droid.org/zh_Hans/packages/com.termux/" title="下载链接">下载链接</a><br>Anlinux下载:<a href="https://f-droid.org/zh_Hans/packages/exa.lnx.a/" title="下载链接">下载链接</a></p><ol><li>授予Termux文件访问权限，运行以下命令<br><code>termux-setup-storage</code></li><li>换源，一键命令<br>打开你的Termux<img src="https://s1.ax1x.com/2020/06/28/Ngw86P.jpg" alt="Termux" border="0"><figure class="highlight shell"><table><tr><td class="gutter hljs"><div class="hljs code-wrapper"><pre><span class="line">1</span><br><span class="line">2</span><br><span class="line">3</span><br><span class="line">4</span><br><span class="line">5</span><br><span class="line">6</span><br><span class="line">7</span><br></pre></div></td><td class="code"><div class="hljs code-wrapper"><pre><code class="hljs shell">sed -i &amp;#039;s@^\(deb.*stable main\)$@#\1\ndeb https://mirrors.tuna.tsinghua.edu.cn/termux/termux-packages-24 stable main@&amp;#039; $PREFIX/etc/apt/sources.list<br><br>sed -i &amp;#039;s@^\(deb.*games stable\)$@#\1\ndeb https://mirrors.tuna.tsinghua.edu.cn/termux/game-packages-24 games stable@&amp;#039; $PREFIX/etc/apt/sources.list.d/game.list<br><br>sed -i &amp;#039;s@^\(deb.*science stable\)$@#\1\ndeb https://mirrors.tuna.tsinghua.edu.cn/termux/science-packages-24 science stable@&amp;#039; $PREFIX/etc/apt/sources.list.d/science.list<br><br>pkg update<br></code></pre></div></td></tr></table></figure>等待几秒就好了</li><li>开始安装Linux<br>还记得Anlinux吗？对，我们接下来要用他来安装<br>首先你进来是这样的</li></ol><img src="https://s1.ax1x.com/2020/06/28/Ng0dHO.jpg" alt="Anlinux" border="0"><p>点击选择，选你想要的系统</p><p>这里我选择的是Ubuntu</p><img src="https://s1.ax1x.com/2020/06/28/Ng02KP.jpg" alt="Ubuntu" border="0"><p>复制他给你的命令到Termux运行，安装过程略</p><p>安装好之后，该如何运行呢？</p><p>以Ubuntu为例</p><p>输入以下命令到Termux</p><p><code>./start-ubuntu.sh</code></p><img src="https://s1.ax1x.com/2020/06/28/Ng0qK0.jpg" alt="Start Ubutnu" border="0"><hr><h1 id="完成"><a href="#完成" class="headerlink" title="完成"></a>完成</h1>]]></content>
    
    
    
    <tags>
      
      <tag>Termux</tag>
      
    </tags>
    
  </entry>
  
  
  
  
</search>
